{
  "format_version": "1.10.0",
  "minecraft:client_entity": {
    "description": {
      "identifier": "guxi:energy_light",
      "materials": {
        "default": "entity_alphatest"
      },
      "textures": {
        "default": "textures/guxi/view/white",
        "light_gold": "textures/guxi/view/gold",
        "light_black": "textures/guxi/view/black"
      },
      "geometry": {
        "default": "geometry.energy_light"
      },
      "particle_effects": {
        "light": "minecraft:endrod"
      },
      "render_controllers": [ "controller.render.energy_light" ],
      "animations": {
        "light": "animation.energy.light"
      },
      "scripts": {
        "animate": [
          "light"
        ]
      }
    }
  }
} 