{
    "format_version": "1.17.10",
    "minecraft:entity": {
        "description": {
            "identifier": "minecraft:player",
            "is_spawnable": false,
            "is_summonable": false,
            "is_experimental": false
        },
        
        "events": {
        },

        "component_groups": {
        },

        "components": {
            // the basic components of player entity
            "minecraft:type_family": { "family": [ "player" ] },
            "minecraft:nameable": { "always_show": true, "allow_name_tag_renaming": false },
            "minecraft:is_hidden_when_invisible": {},
            "minecraft:loot": { "table": "loot_tables/empty.json" },
            "minecraft:collision_box": { "width": 0.6, "height": 1.8 },
            "minecraft:movement": { "value": 0.1 },
            "minecraft:physics": {},
            "minecraft:conditional_bandwidth_optimization": {},
            "minecraft:player.saturation": { "value": 20 },
            "minecraft:player.exhaustion": { "value": 0, "max": 4 },
            "minecraft:player.level": { "value": 0, "max": 24791 },
            "minecraft:player.experience": { "value": 0, "max": 1 }
        }
    }
}
